YouTubeWrapped/Wrapped.py
YouTubeWrapped/WrappedTemplate.jpg
YouTubeWrapped/__init__.py
YouTubeWrapped/Js_assets/login.js
YouTubeWrapped/Js_assets/package-lock.json
YouTubeWrapped/Js_assets/package.json
youtubewrapped-1.8.dist-info/METADATA
youtubewrapped-1.8.dist-info/WHEEL
youtubewrapped-1.8.dist-info/licenses/LICENSE.md
youtubewrapped-1.8.dist-info/RECORD
