Metadata-Version: 2.3
Name: YouTubeWrapped
Version: 1.8
Summary: Analyze your YouTube watch history and get your Youtube Wrapped for the year!
Project-URL: Homepage, https://github.com/haziq-exe/YouTubeWrapped
Author-email: Haziq <haziqmk123@gmail.com>
Keywords: Youtube Wrapped,data-analysis,playwright,wrapped,youtube
Classifier: License :: OSI Approved :: MIT License
Classifier: Operating System :: OS Independent
Classifier: Programming Language :: Python :: 3
Classifier: Programming Language :: Python :: 3.8
Classifier: Programming Language :: Python :: 3.9
Classifier: Programming Language :: Python :: 3.10
Classifier: Programming Language :: Python :: 3.11
Requires-Dist: beautifulsoup4>=4.0.0
Requires-Dist: openpyxl>=3.0.10
Requires-Dist: pandas>=1.0.0
Requires-Dist: pillow>=8.0.0
Requires-Dist: playwright>=1.0.0
Requires-Dist: requests>=2.0.0
